Metadata-Version: 2.1
Name: discord-logger
Version: 1.2.5
Summary: Discord Logger is a custom message logger to Discord for Python 3
Home-page: https://github.com/chinnichaitanya/python-discord-logger
Author: Chaitanya Chinni
License: MIT License
Keywords: monitoring,discord,messaging,logging,health-check,notification-service,notification,discord-webhook
Platform: UNKNOWN
Classifier: Environment :: Web Environment
Classifier: Intended Audience :: Developers
Classifier: License :: OSI Approved :: MIT License
Classifier: Operating System :: OS Independent
Classifier: Programming Language :: Python :: 3
Classifier: Topic :: Internet :: WWW/HTTP
Classifier: Topic :: Internet :: WWW/HTTP :: Dynamic Content
Requires-Python: >=3.6
License-File: LICENSE
Requires-Dist: discord-webhook (==0.15.0)
Requires-Dist: pyyaml (==6.0.1)
